Adder_APB/Adder_APB.srcs/sources_1/new/Adder.vhd
----------------------------------------------------------------------------------
-- Company: 
-- Engineer: 
-- 
-- Create Date: 02/22/2023 07:40:49 PM
-- Design Name: 
-- Module Name: Adder - Behavioral
-- Project Name: 
-- Target Devices: 
-- Tool Versions: 
-- Description: 
-- 
-- Dependencies: 
-- 
-- Revision:
-- Revision 0.01 - File Created
-- Additional Comments:
-- 
----------------------------------------------------------------------------------


library IEEE;
use IEEE.STD_LOGIC_1164.ALL;
use IEEE.NUMERIC_STD.ALL;

-- AUTHOR: Hasan Al-Shaikh

-- This ADDER module is a simple APB master entity. For simplicity's sake some signals (e.g. STB, SLV_ERR) from the protocol has been eliminated
-- We further assume that the input add_i is going to be asserted only for a cycle before being deasserted.
entity apb_master_adder is
    Port ( pclk : in STD_LOGIC;
           preset_n : in STD_LOGIC;
           add_i : in STD_LOGIC_VECTOR (1 downto 0); -- 00: NOP, 01- READ, 10- NOP, 11- WRITE
           
           psel_o : out STD_LOGIC;
           penable_o : out STD_LOGIC;
           paddr_o : out STD_LOGIC_VECTOR (31 downto 0);
           pwrite_o : out STD_LOGIC;
           pwdata_o : out STD_LOGIC_VECTOR (31 downto 0);
           
           prdata_i : in STD_LOGIC_VECTOR (31 downto 0);
           pready_i : in STD_LOGIC);
end apb_master_adder;

architecture Behavioral of apb_master_adder is

type state_t is (IDLE, SETUP, ACESS);
signal state_r: state_t;
signal apb_acess_state:  STD_LOGIC :='0';
signal pwrite_o_t: STD_LOGIC;
signal pread_data: std_logic_vector(prdata_i'range);
signal pwdata_o_t: std_logic_vector (pwdata_o'range);
--signal add_i_high: std_logic ;
begin
    --add_i_high<=add_i(1);
    pwrite_o<=pwrite_o_t;
    process (pclk, preset_n)
    begin
        if (preset_n='0') then 
            state_r<=IDLE;
            psel_o<='0';
            penable_o<='0';
            pwrite_o_t<='0';
            pread_data <=(others=>'0');
            paddr_o<=(others=>'0');
            pwdata_o<=(others=>'0');
            --add_i_high<='0';
        elsif(rising_edge (pclk)) then
            case state_r is 
            when IDLE=>
                psel_o<='0';
                penable_o<='0';
 --               if (pwrite_o_t='0' and pready_i='1') then -- IF WE DO HERE THIS, this is not an accurate capture of the intent of the protocol. 
                                                            -- pready will come only while the master is in ACESS STATE
 --                     pread_data<=prdata_i; 
 --               end if;
                if (add_i(0)='1') then
                    state_r<=SETUP; 
                    pwrite_o_t<=add_i(1);-- We have to keep pwrite_o asserted after which operation to perform which is why 
                                    -- we flopped pwrite_o. Additionally, this has to be asserted as soon as p_enable_o is asserted                  
                else
                    state_r<=IDLE;                    
                end if;
            when SETUP=>
                
                psel_o<='1';
                penable_o<='0';     
                state_r<=ACESS;
            when ACESS=>
                --psel_o<='1'; 
                if (pwrite_o_t='1') then
                    pwdata_o<=pwdata_o_t;
                end if;
                paddr_o<=(31=> '1', 30=>'0', 29=>'1', 28=>'0', others=>'0'); -- APB ADDRESS: We assume only one adddress (32'hA000) to be written to / read from
                
                penable_o<='1'; -- penable should become high one cycle afer psel_o as psel_o is asserted in SETUP state. 
                                -- We enter ACESS state automatically one cycle later.
                if (pready_i='1') then
                    state_r<=IDLE;   -- We are not supporting back to back transactions. 
                                     -- We assume that for one assertion of PSEL_O, only one PEN_O assertion will happen 
                    if (pwrite_o_t='0') then -- EKHON KAR JE VALUE ACHE, SEITA NIYE NEXT STATE E DHUKTE HOILE OI STATE
                        pread_data<=prdata_i;
                    end if;                                                 
                else
                    state_r<=ACESS;
                    apb_acess_state<='1';
                  end if;   
            when others=> null;
            end case;
        end if;
    end process;
    
--    IF WE DO HERE THE FOLLOWING, IT's A GROSS VIOLATION OF DR. STITT's 1 PROCESS FSM CODING GUIDELINES. DONT DO IT.
--    ASSIGN ALL OUTPUTS/SIGNALS CORRESPONDING TO THE STATES IN THE SAME PROCESS BLOCK.
--    process (state_r) begin
--        if (state_r=ACESS) then
--            apb_acess_state<='1';
--        else
--            apb_acess_state<='0';
--        end if;
--    end process;

-- 
--    with apb_acess_state select
--    paddr_o<=(31=> '1', 30=>'0', 29=>'1', 28=>'0', others=>'0') when '1', 
--            (others=>'0') when others;



                
    -- PWDATA_O
    -- Read a value from the slave at address 0xA000 => This is already done in the 
    -- Increment that value
    -- Sned that value back during the write operation to address 0xA000
    process (pread_data) begin
        pwdata_o_t<= std_logic_vector(unsigned(pread_data)+1);
    end process;
end Behavioral;

Adder_APB/Adder_APB.srcs/sim_1/new/apb_slave_tb.sv
`timescale 1ns / 1ps
//////////////////////////////////////////////////////////////////////////////////
// Company: 
// Engineer: 
// 
// Create Date: 02/22/2023 09:52:18 PM
// Design Name: 
// Module Name: apb_slave_tb
// Project Name: 
// Target Devices: 
// Tool Versions: 
// Description: 
// 
// Dependencies: 
// 
// Revision:
// Revision 0.01 - File Created
// Additional Comments:
// 
//////////////////////////////////////////////////////////////////////////////////


`define CLK @(posedge pclk)

module apb_slave_tb ();
  
	logic 			pclk;
	logic 			preset_n; 	// Active low reset
 
  logic[1:0]		add_i;		// 2'b00 - NOP, 2'b01 - READ, 2'b11 - WRITE
  
	logic 			psel_o;
	logic 			penable_o;
  	logic [31:0]	paddr_o;
	logic			pwrite_o;
  	logic [31:0] 	pwdata_o;
  	logic [31:0]	prdata_i;
 	logic			pready_i;
  
  // Implement clock
  always begin
    pclk = 1'b0;
    #5;
    pclk = 1'b1;
    #5;
  end
  
  // Instantiate the RTL
  apb_master_adder APB_MASTER (.pclk(pclk),
  .preset_n(preset_n),
  .add_i(add_i),
  .psel_o(psel_o),
  .penable_o(penable_o),
  .paddr_o(paddr_o),
  .pwrite_o(pwrite_o),
  .pwdata_o(pwdata_o),
  .prdata_i(prdata_i),
  .pready_i(pready_i) 
  );
  
  // Drive stimulus
  initial begin
    preset_n = 1'b0;
    add_i = 2'b00;
    repeat (2) `CLK;
    preset_n = 1'b1;
    repeat (2) `CLK;
    
    // Initiate a read transaction
    add_i = 2'b01;
    `CLK;
    add_i = 2'b00;
    repeat (4) `CLK;
    
    // Initiate a write transaction
    add_i = 2'b11;
    `CLK;
    add_i = 2'b00;
    repeat (4) `CLK;
    $finish();
  end
  
  // APB Slave
  always_ff @(posedge pclk or negedge preset_n) begin
    if (~preset_n)
      pready_i <= 1'b0;
    else begin
        if (psel_o && penable_o) begin
          pready_i <= 1'b1;
          prdata_i <= $urandom%32'h20;
        end else begin
          pready_i <= 1'b0;
          prdata_i <= $urandom%32'hFF;
        end
    end
  end
  
  // VCD Dump
  initial begin
    $dumpfile("apb_master.vcd");
    $dumpvars(2, apb_slave_tb);
  end
  
endmodule

Adder_APB/Adder_APB.sim/sim_1/behav/xsim/apb_master.vcd
$date
   Thu Feb 23 02:41:32 2023
$end
$version
  2020.2
$end
$timescale
  1ps
$end
$scope module apb_slave_tb $end
$var reg 1 ! pclk $end
$var reg 1 " preset_n $end
$var reg 2 # add_i [1:0] $end
$var reg 1 $ psel_o $end
$var reg 1 % penable_o $end
$var reg 32 & paddr_o [31:0] $end
$var reg 1 ' pwrite_o $end
$var reg 32 ( pwdata_o [31:0] $end
$var reg 32 ) prdata_i [31:0] $end
$var reg 1 * pready_i $end
$scope module APB_MASTER $end
$var wire 1 + pclk $end
$var wire 1 , preset_n $end
$var wire 2 - add_i [1:0] $end
$var wire 1 . psel_o $end
$var wire 1 / penable_o $end
$var wire 32 0 paddr_o [31:0] $end
$var wire 1 1 pwrite_o $end
$var wire 32 2 pwdata_o [31:0] $end
$var wire 32 3 prdata_i [31:0] $end
$var wire 1 4 pready_i $end
$var wire 1 5 apb_acess_state $end
$var wire 1 6 pwrite_o_t $end
$var wire 32 7 pread_data [31:0] $end
$var wire 32 8 pwdata_o_t [31:0] $end
$upscope $end
$upscope $end
$enddefinitions $end
#0
$dumpvars
0!
0"
b0 #
0$
0%
b0 &
0'
b0 (
bx )
0*
0+
0,
b0 -
0.
0/
b0 0
01
b0 2
bx 3
04
05
06
b0 7
b1 8
$end
#5000
1!
0*
1+
#10000
0!
0+
#15000
1!
1"
b111011 )
0*
1+
1,
b111011 3
#20000
0!
0+
#25000
1!
b11110001 )
0*
1+
b11110001 3
#30000
0!
0+
#35000
1!
b1 #
b10000001 )
0*
1+
b1 -
b10000001 3
#40000
0!
0+
#45000
1!
b0 #
1$
b101100 )
0*
1+
b0 -
1.
b101100 3
#50000
0!
0+
#55000
1!
1%
b10100000000000000000000000000000 &
b10001101 )
0*
1+
1/
b10100000000000000000000000000000 0
b10001101 3
15
#60000
0!
0+
#65000
1!
b11101 )
1*
1+
b11101 3
14
#70000
0!
0+
#75000
1!
b11110 )
1*
1+
b11110 3
b11101 7
b11110 8
#80000
0!
0+
#85000
1!
b11 #
0$
0%
1'
b1011 )
1*
1+
b11 -
0.
0/
11
b1011 3
16
#90000
0!
0+
#95000
1!
b0 #
1$
b1001000 )
0*
1+
b0 -
1.
b1001000 3
04
#100000
0!
0+
#105000
1!
1%
b11110 (
b1010010 )
0*
1+
1/
b11110 2
b1010010 3
#110000
0!
0+
#115000
1!
b11001 )
1*
1+
b11001 3
14
#120000
0!
0+
#125000
1!
b1001 )
1*
1+
b1001 3
